ier/__init__.py
ier/_summary.py
ier/_validation.py
ier/composite.py
ier/evenodd.py
ier/guttman.py
ier/infrequency.py
ier/irv.py
ier/longstring.py
ier/lz.py
ier/mad.py
ier/mahad.py
ier/markov.py
ier/onset.py
ier/person_total.py
ier/psychsyn.py
ier/reliability.py
ier/response_time.py
ier/semantic.py
ier/u3_poly.py
insufficient_effort-1.5.0.dist-info/licenses/LICENSE
insufficient_effort-1.5.0.dist-info/METADATA
insufficient_effort-1.5.0.dist-info/WHEEL
insufficient_effort-1.5.0.dist-info/top_level.txt
insufficient_effort-1.5.0.dist-info/RECORD
