Metadata-Version: 2.4
Name: insufficient-effort
Version: 1.5.0
Summary: Python library for detecting Insufficient Effort Responding (IER) in survey data
Author-email: Cameron Lyons <cameron.lyons2@gmail.com>
Project-URL: Homepage, https://github.com/Cameron-Lyons/ier
Project-URL: Bug Tracker, https://github.com/Cameron-Lyons/ier/issues
Classifier: Programming Language :: Python :: 3
Classifier: License :: OSI Approved :: MIT License
Classifier: Operating System :: OS Independent
Requires-Python: >=3.11
License-File: LICENSE
Requires-Dist: numpy>=1.26.0
Provides-Extra: full
Requires-Dist: scipy>=1.11.0; extra == "full"
Provides-Extra: plot
Requires-Dist: matplotlib>=3.8.0; extra == "plot"
Provides-Extra: dev
Requires-Dist: scipy>=1.16.3; extra == "dev"
Requires-Dist: scipy-stubs>=1.16.3; extra == "dev"
Requires-Dist: matplotlib>=3.8.0; extra == "dev"
Requires-Dist: pytest>=9.0.2; extra == "dev"
Requires-Dist: pytest-cov>=7.0.0; extra == "dev"
Requires-Dist: mypy>=1.19.0; extra == "dev"
Requires-Dist: ruff>=0.14.0; extra == "dev"
Requires-Dist: pylint>=4.0.0; extra == "dev"
Requires-Dist: bandit>=1.9.0; extra == "dev"
Requires-Dist: pip-audit>=2.9.0; extra == "dev"
Requires-Dist: hypothesis>=6.150.0; extra == "dev"
Requires-Dist: pre-commit>=4.0.0; extra == "dev"
Dynamic: license-file
